Workbook

Sheet Pay_Item_Catalog
A1: Item Code | B1: Description | C1: Unit | D1: Category | E1: Active
A2: HDD_FT | B2: Horizontal Directional Drilling | C2: FT | D2: Installation | E2: Yes
A3: TRENCH_FT | B3: Open Trench Installation | C3: FT | D3: Installation | E3: Yes
A4: HANDHOLE_EA | B4: Handhole Installation | C4: EA | D4: Structure | E4: Yes
A5: VAULT_EA | B5: Vault Installation | C5: EA | D5: Structure | E5: Yes
A6: POTHOLE_EA | B6: Potholing | C6: EA | D6: Investigation | E6: Yes
A7: RESTORATION_SQFT | B7: Area Restoration | C7: SQFT | D7: Restoration | E7: Yes
A8: BORE_FT | B8: Boring (ft) | C8: FT | D8: Installation | E8: Yes
A9: CABLE_PULL_FT | B9: Cable Pulling | C9: FT | D9: Installation | E9: Yes
A10: CONDUIT_FT | B10: Conduit Installation | C10: FT | D10: Installation | E10: Yes
A11: REWORK_FT | B11: Rework (discounted) | C11: FT | D11: Correction | E11: Yes

Sheet Rate_Table
A1: Rate ID | B1: Pay Item Code | C1: Rate Amount | D1: Rate Unit | E1: Effective From | F1: Effective To | G1: Context/Notes
A2: R001 | B2: HDD_FT | C2: 0.85 | D2: per FT | E2: 2026-01-01 | F2: 2026-12-31 | G2: Urban HDD standard
A3: R002 | B3: TRENCH_FT | C3: 0.65 | D3: per FT | E3: 2026-01-01 | F3: 2026-12-31 | G3: Open trench standard
A4: R003 | B4: HANDHOLE_EA | C4: 45 | D4: per EA | E4: 2026-01-01 | F4: 2026-12-31 | G4: Standard handhole
A5: R004 | B5: VAULT_EA | C5: 85 | D5: per EA | E5: 2026-01-01 | F5: 2026-12-31 | G5: Standard vault | L5: Pay Item Code | M5: Rate Unit | N5: Context/Notes
A6: R005 | B6: POTHOLE_EA | C6: 35 | D6: per EA | E6: 2026-01-01 | F6: 2026-12-31 | G6: Standard pothole | L6: HDD_FT | M6: per FT | N6: Urban HDD standard
A7: R006 | B7: RESTORATION_SQFT | C7: 2.5 | D7: per SQFT | E7: 2026-01-01 | F7: 2026-12-31 | G7: Area restoration | L7: TRENCH_FT | M7: per FT | N7: Open trench standard
A8: R007 | B8: BORE_FT | C8: 0.9 | D8: per FT | E8: 2026-01-01 | F8: 2026-12-31 | G8: Difficult soil | L8: HANDHOLE_EA | M8: per EA | N8: Standard handhole
A9: R008 | B9: CABLE_PULL_FT | C9: 0.4 | D9: per FT | E9: 2026-01-01 | F9: 2026-12-31 | G9: Standard cable pull | L9: VAULT_EA | M9: per EA | N9: Standard vault
A10: R009 | B10: CONDUIT_FT | C10: 0.55 | D10: per FT | E10: 2026-01-01 | F10: 2026-12-31 | G10: Standard conduit | L10: POTHOLE_EA | M10: per EA | N10: Standard pothole
A11: R010 | B11: REWORK_FT | C11: 0.3 | D11: per FT | E11: 2026-01-01 | F11: 2026-12-31 | G11: Rework penalty rate | L11: RESTORATION_SQFT | M11: per SQFT | N11: Area restoration
L12: BORE_FT | M12: per FT | N12: Difficult soil
L13: CABLE_PULL_FT | M13: per FT | N13: Standard cable pull
L14: CONDUIT_FT | M14: per FT | N14: Standard conduit
L15: REWORK_FT | M15: per FT | N15: Rework penalty rate
L19: Equipe de Perfuração Direcional (HDD Crew) | M19: Diária
L20: Foreman (Encarregado de Equipe): | M20: $200
L21: HDD Driller (Operador de Perfuratriz): | M21: $200
L22: HDD Locator / Tracker (Localizador): | M22: $200
L23: Mud Mixer / Laborer (Auxiliar de Mistura): | M23: $170
L24: Operator (Operador de Escavadeira/Mini-carregadeira): | M24: $200
L25: Restoration Laborer (Auxiliar de Restauração): | M25: $160
L26: Manager | M26: $250
L28: Em caso de meia diária (0.5): é sempre exatamente metade do mínimo (50%)? | M28: sempre a metade - 50%
L29: REWORK_FT: você quer que seja desconto do pool (penalidade) ou apenas “paga menos” (entra positivo com rate menor)?pool (penalidade) ou apenas “paga menos” (entra positivo com rate menor)? | M29: 50/50

Sheet Workers
A1: Worker ID | B1: Name | C1: Employee Type | D1: Base Hourly Rate | E1: OT Multiplier | F1: Min Hourly Guarantee | G1: Piece Rate Enabled | H1: Active
A2: W001 | B2: John Silva | C2: W2 | D2: 18 | E2: 1.5 | F2: Yes | G2: Yes | H2: Yes
A3: W002 | B3: Maria Santos | C3: W2 | D3: 20 | E3: 1.5 | F3: Yes | G3: Yes | H3: Yes
A4: W003 | B4: Carlos Mendes | C4: 1099 | D4: 22 | E4: 1 | F4: No | G4: Yes | H4: Yes
A5: W004 | B5: Pedro Costa | C5: W2 | D5: 17.5 | E5: 1.5 | F5: Yes | G5: Yes | H5: Yes
A6: W005 | B6: Ana Lima | C6: W2 | D6: 19 | E6: 1.5 | F6: Yes | G6: Yes | H6: Yes
A7: W006 | B7: Jose Oliveira | C7: W2 | D7: 18.5 | E7: 1.5 | F7: Yes | G7: Yes | H7: Yes

Sheet Time_Entry
A1: Entry ID | B1: Date | C1: Worker ID | D1: Worker Name | E1: Clock In | F1: Clock Out | G1: Break (min) | H1: Total Hours | I1: Crew | J1: Notes
A2: TE001 | B2: 2026-01-27 | C2: W001 | D2: John Silva | E2: 07:00 | F2: 16:30 | G2: 30 | H2: =(F2-E2)*24-G2/60 -> 9 | I2: Crew A | J2: Normal shift
A3: TE002 | B3: 2026-01-27 | C3: W002 | D3: Maria Santos | E3: 07:00 | F3: 16:30 | G3: 30 | H3: =(F3-E3)*24-G3/60 -> 9 | I3: Crew A | J3: Normal shift
A4: TE003 | B4: 2026-01-27 | C4: W004 | D4: Pedro Costa | E4: 07:00 | F4: 16:30 | G4: 30 | H4: =(F4-E4)*24-G4/60 -> 9 | I4: Crew B | J4: Normal shift
A5: TE004 | B5: 2026-01-28 | C5: W001 | D5: John Silva | E5: 07:00 | F5: 17:00 | G5: 30 | H5: =(F5-E5)*24-G5/60 -> 9.5 | I5: Crew A | J5: Extended day
A6: TE005 | B6: 2026-01-28 | C6: W002 | D6: Maria Santos | E6: 07:00 | F6: 17:00 | G6: 30 | H6: =(F6-E6)*24-G6/60 -> 9.5 | I6: Crew A | J6: Extended day
A7: TE006 | B7: 2026-01-28 | C7: W004 | D7: Pedro Costa | E7: 07:00 | F7: 16:30 | G7: 30 | H7: =(F7-E7)*24-G7/60 -> 9 | I7: Crew B | J7: Normal shift
A8: TE007 | B8: 2026-01-29 | C8: W001 | D8: John Silva | E8: 07:00 | F8: 18:00 | G8: 30 | H8: =(F8-E8)*24-G8/60 -> 10.5 | I8: Crew A | J8: Long day
A9: TE008 | B9: 2026-01-29 | C9: W002 | D9: Maria Santos | E9: 07:00 | F9: 18:00 | G9: 30 | H9: =(F9-E9)*24-G9/60 -> 10.5 | I9: Crew A | J9: Long day
A10: TE009 | B10: 2026-01-29 | C10: W004 | D10: Pedro Costa | E10: 07:00 | F10: 17:00 | G10: 30 | H10: =(F10-E10)*24-G10/60 -> 9.5 | I10: Crew B | J10: Extended day
A11: TE010 | B11: 2026-01-30 | C11: W001 | D11: John Silva | E11: 07:00 | F11: 16:30 | G11: 30 | H11: =(F11-E11)*24-G11/60 -> 9 | I11: Crew A | J11: Normal shift
A12: TE011 | B12: 2026-01-30 | C12: W002 | D12: Maria Santos | E12: 07:00 | F12: 16:30 | G12: 30 | H12: =(F12-E12)*24-G12/60 -> 9 | I12: Crew A | J12: Normal shift
A13: TE012 | B13: 2026-01-30 | C13: W004 | D13: Pedro Costa | E13: 07:00 | F13: 16:30 | G13: 30 | H13: =(F13-E13)*24-G13/60 -> 9 | I13: Crew B | J13: Normal shift
... A16: TE015 | B16: 2026-01-31 | C16: W004 | D16: Pedro Costa | E16: 07:00 | F16: 17:00 | G16: 30 | H16: =(F16-E16)*24-G16/60 -> 9.5 | I16: Crew B | J16: Friday finish

Sheet Production_Entry
A1: Prod ID | B1: Date | C1: Worker ID | D1: Worker Name | E1: Crew | F1: Pay Item Code | G1: Quantity | H1: Unit | I1: Status | J1: Notes
A2: P001 | B2: 2026-01-27 | C2: W001 | D2: John Silva | E2: Crew A | F2: HDD_FT | G2: 450 | H2: FT | I2: Approved | J2: Good progress
A3: P002 | B3: 2026-01-27 | C3: W002 | D3: Maria Santos | E3: Crew A | F3: HDD_FT | G3: 450 | H3: FT | I3: Approved | J3: Good progress
A4: P003 | B4: 2026-01-27 | C4: W004 | D4: Pedro Costa | E4: Crew B | F4: TRENCH_FT | G4: 320 | H4: FT | I4: Approved | J4: Standard trench
A5: P004 | B5: 2026-01-27 | C5: W004 | D5: Pedro Costa | E5: Crew B | F5: HANDHOLE_EA | G5: 2 | H5: EA | I5: Approved | J5: 2 handholes
A6: P005 | B6: 2026-01-28 | C6: W001 | D6: John Silva | E6: Crew A | F6: HDD_FT | G6: 520 | H6: FT | I6: Approved | J6: Excellent day
A7: P006 | B7: 2026-01-28 | C7: W002 | D7: Maria Santos | E7: Crew A | F7: HDD_FT | G7: 520 | H7: FT | I7: Approved | J7: Excellent day
A8: P007 | B8: 2026-01-28 | C8: W004 | D8: Pedro Costa | E8: Crew B | F8: TRENCH_FT | G8: 380 | H8: FT | I8: Approved | J8: Good pace
A9: P008 | B9: 2026-01-28 | C9: W004 | D9: Pedro Costa | E9: Crew B | F9: VAULT_EA | G9: 1 | H9: EA | I9: Approved | J9: 1 vault
A10: P009 | B10: 2026-01-29 | C10: W001 | D10: John Silva | E10: Crew A | F10: HDD_FT | G10: 610 | H10: FT | I10: Approved | J10: Long day productive
A11: P010 | B11: 2026-01-29 | C11: W002 | D11: Maria Santos | E11: Crew A | F11: HDD_FT | G11: 610 | H11: FT | I11: Approved | J11: Long day productive
A12: P011 | B12: 2026-01-29 | C12: W004 | D12: Pedro Costa | E12: Crew B | F12: TRENCH_FT | G12: 420 | H12: FT | I12: Approved | J12: Extended hours
A13: P012 | B13: 2026-01-29 | C13: W004 | D13: Pedro Costa | E13: Crew B | F13: HANDHOLE_EA | G13: 3 | H13: EA | I13: Approved | J13: 3 handholes
... A26: P025 | B26: 2026-01-31 | C26: W004 | D26: Pedro Costa | E26: Crew B | F26: VAULT_EA | G26: 1 | H26: EA | I26: Approved | J26: Final vault

Sheet Payroll_Calculation
A1: Worker ID | B1: Worker Name | C1: Period | D1: Total Hours | E1: Regular Hours | F1: OT Hours | G1: Piece Earnings | H1: Hourly Earnings | I1: OT Premium | J1: Min Guarantee | K1: Total Pay | L1: Payment Method
A2: Pay Period: Jan 27 - Jan 31, 2026
A4: W001 | B4: John Silva | C4: Week 5 | D4: =SUMIFS(Time_Entry!H:H,Time_Entry!C:C,A4) -> 48 | E4: =MIN(D4,40) -> 40 | F4: =MAX(D4-40,0) -> 8 | G4: =SUMPRODUCT((Production_Entry!$C$2:$C$26=A4)*(Production_Entry!$G$2:$G$26),VLOOKUP(Production_Entry!$F$2:$F$26,Rate_Table!$B$2:$C$11,2,0)) -> #VALUE! | H4: =E4*VLOOKUP(A4,Workers!$A$2:$D$7,4,FALSE) -> 720 | I4: =F4*VLOOKUP(A4,Workers!$A$2:$D$7,4,FALSE)*(VLOOKUP(A4,Workers!$A$2:$E$7,5,FALSE)-1) -> 72 | J4: =D4*VLOOKUP(A4,Workers!$A$2:$D$7,4,FALSE) -> 864 | K4: =MAX(G4,J4)+I4 -> #VALUE! | L4: Piece Rate + OT
A5: W002 | B5: Maria Santos | C5: Week 5 | D5: =SUMIFS(Time_Entry!H:H,Time_Entry!C:C,A5) -> 48 | E5: =MIN(D5,40) -> 40 | F5: =MAX(D5-40,0) -> 8 | G5: =SUMPRODUCT((Production_Entry!$C$2:$C$26=A5)*(Production_Entry!$G$2:$G$26),VLOOKUP(Production_Entry!$F$2:$F$26,Rate_Table!$B$2:$C$11,2,0)) -> #VALUE! | H5: =E5*VLOOKUP(A5,Workers!$A$2:$D$7,4,FALSE) -> 800 | I5: =F5*VLOOKUP(A5,Workers!$A$2:$D$7,4,FALSE)*(VLOOKUP(A5,Workers!$A$2:$E$7,5,FALSE)-1) -> 80 | J5: =D5*VLOOKUP(A5,Workers!$A$2:$D$7,4,FALSE) -> 960 | K5: =MAX(G5,J5)+I5 -> #VALUE! | L5: Piece Rate + OT
A6: W003 | B6: Carlos Mendes | C6: Week 5 | D6: =SUMIFS(Time_Entry!H:H,Time_Entry!C:C,A6) -> 0 | E6: =MIN(D6,40) -> 0 | F6: =MAX(D6-40,0) -> 0 | G6: =SUMPRODUCT((Production_Entry!$C$2:$C$26=A6)*(Production_Entry!$G$2:$G$26),VLOOKUP(Production_Entry!$F$2:$F$26,Rate_Table!$B$2:$C$11,2,0)) -> #VALUE! | H6: =E6*VLOOKUP(A6,Workers!$A$2:$D$7,4,FALSE) -> 0 | I6: =F6*VLOOKUP(A6,Workers!$A$2:$D$7,4,FALSE)*(VLOOKUP(A6,Workers!$A$2:$E$7,5,FALSE)-1) -> 0 | J6: =D6*VLOOKUP(A6,Workers!$A$2:$D$7,4,FALSE) -> 0 | K6: =MAX(G6,J6)+I6 -> #VALUE! | L6: Piece Rate + OT
A7: W004 | B7: Pedro Costa | C7: Week 5 | D7: =SUMIFS(Time_Entry!H:H,Time_Entry!C:C,A7) -> 46 | E7: =MIN(D7,40) -> 40 | F7: =MAX(D7-40,0) -> 6 | G7: =SUMPRODUCT((Production_Entry!$C$2:$C$26=A7)*(Production_Entry!$G$2:$G$26),VLOOKUP(Production_Entry!$F$2:$F$26,Rate_Table!$B$2:$C$11,2,0)) -> #VALUE! | H7: =E7*VLOOKUP(A7,Workers!$A$2:$D$7,4,FALSE) -> 700 | I7: =F7*VLOOKUP(A7,Workers!$A$2:$D$7,4,FALSE)*(VLOOKUP(A7,Workers!$A$2:$E$7,5,FALSE)-1) -> 52.5 | J7: =D7*VLOOKUP(A7,Workers!$A$2:$D$7,4,FALSE) -> 805 | K7: =MAX(G7,J7)+I7 -> #VALUE! | L7: Piece Rate + OT
A8: W005 | B8: Ana Lima | C8: Week 5 | D8: =SUMIFS(Time_Entry!H:H,Time_Entry!C:C,A8) -> 0 | E8: =MIN(D8,40) -> 0 | F8: =MAX(D8-40,0) -> 0 | G8: =SUMPRODUCT((Production_Entry!$C$2:$C$26=A8)*(Production_Entry!$G$2:$G$26),VLOOKUP(Production_Entry!$F$2:$F$26,Rate_Table!$B$2:$C$11,2,0)) -> #VALUE! | H8: =E8*VLOOKUP(A8,Workers!$A$2:$D$7,4,FALSE) -> 0 | I8: =F8*VLOOKUP(A8,Workers!$A$2:$D$7,4,FALSE)*(VLOOKUP(A8,Workers!$A$2:$E$7,5,FALSE)-1) -> 0 | J8: =D8*VLOOKUP(A8,Workers!$A$2:$D$7,4,FALSE) -> 0 | K8: =MAX(G8,J8)+I8 -> #VALUE! | L8: Piece Rate + OT
A9: W006 | B9: Jose Oliveira | C9: Week 5 | D9: =SUMIFS(Time_Entry!H:H,Time_Entry!C:C,A9) -> 0 | E9: =MIN(D9,40) -> 0 | F9: =MAX(D9-40,0) -> 0 | G9: =SUMPRODUCT((Production_Entry!$C$2:$C$26=A9)*(Production_Entry!$G$2:$G$26),VLOOKUP(Production_Entry!$F$2:$F$26,Rate_Table!$B$2:$C$11,2,0)) -> #VALUE! | H9: =E9*VLOOKUP(A9,Workers!$A$2:$D$7,4,FALSE) -> 0 | I9: =F9*VLOOKUP(A9,Workers!$A$2:$D$7,4,FALSE)*(VLOOKUP(A9,Workers!$A$2:$E$7,5,FALSE)-1) -> 0 | J9: =D9*VLOOKUP(A9,Workers!$A$2:$D$7,4,FALSE) -> 0 | K9: =MAX(G9,J9)+I9 -> #VALUE! | L9: Piece Rate + OT
A11: TOTAL | D11: =SUM(D4:D9) -> 142 | E11: =SUM(E4:E9) -> 120 | F11: =SUM(F4:F9) -> 22 | G11: =SUM(G4:G9) -> #VALUE! | H11: =SUM(H4:H9) -> 2220 | I11: =SUM(I4:I9) -> 204.5 | J11: =SUM(J4:J9) -> 2629 | K11: =SUM(K4:K9) -> #VALUE!

Sheet Dashboard
A1: Payroll Dashboard - Underground Construction
A2: Pay Period: January 27-31, 2026
A4: Total Payroll | B4: =Payroll_Calculation!K11 -> #VALUE!
A5: Total Hours Worked | B5: =Payroll_Calculation!D11 -> 142
A6: Total Piece Earnings | B6: =Payroll_Calculation!G11 -> #VALUE!
A7: Average Rate/Hour | B7: =B4/B5 -> #VALUE!
A9: Top Performers
A10: Worker Name | B10: Total Pay | C10: Hours | D10: Piece Earnings | E10: Avg Rate/Hr
A11: =INDEX(Payroll_Calculation!B:B,MATCH(LARGE(Payroll_Calculation!K:K,1),Payroll_Calculation!K:K,0)) -> #VALUE! | B11: =LARGE(Payroll_Calculation!K:K,1) -> #VALUE! | C11: =INDEX(Payroll_Calculation!D:D,MATCH(LARGE(Payroll_Calculation!K:K,1),Payroll_Calculation!K:K,0)) -> #VALUE! | D11: =INDEX(Payroll_Calculation!G:G,MATCH(LARGE(Payroll_Calculation!K:K,1),Payroll_Calculation!K:K,0)) -> #VALUE! | E11: =B11/C11 -> #VALUE!
A12: =INDEX(Payroll_Calculation!B:B,MATCH(LARGE(Payroll_Calculation!K:K,2),Payroll_Calculation!K:K,0)) -> #VALUE! | B12: =LARGE(Payroll_Calculation!K:K,2) -> #VALUE! | C12: =INDEX(Payroll_Calculation!D:D,MATCH(LARGE(Payroll_Calculation!K:K,2),Payroll_Calculation!K:K,0)) -> #VALUE! | D12: =INDEX(Payroll_Calculation!G:G,MATCH(LARGE(Payroll_Calculation!K:K,2),Payroll_Calculation!K:K,0)) -> #VALUE! | E12: =B12/C12 -> #VALUE!
A13: =INDEX(Payroll_Calculation!B:B,MATCH(LARGE(Payroll_Calculation!K:K,3),Payroll_Calculation!K:K,0)) -> #VALUE! | B13: =LARGE(Payroll_Calculation!K:K,3) -> #VALUE! | C13: =INDEX(Payroll_Calculation!D:D,MATCH(LARGE(Payroll_Calculation!K:K,3),Payroll_Calculation!K:K,0)) -> #VALUE! | D13: =INDEX(Payroll_Calculation!G:G,MATCH(LARGE(Payroll_Calculation!K:K,3),Payroll_Calculation!K:K,0)) -> #VALUE! | E13: =B13/C13 -> #VALUE!
A15: Production Summary
A16: Pay Item | B16: Total Quantity | C16: Unit | D16: Total Value
A17: HDD_FT | B17: =SUMIF(Production_Entry!F:F,A17,Production_Entry!G:G) -> 5220 | C17: =INDEX(Pay_Item_Catalog!C:C,MATCH(A17,Pay_Item_Catalog!A:A,0)) -> FT | D17: =B17*VLOOKUP(A17,Rate_Table!B:C,2,FALSE) -> 4437
A18: TRENCH_FT | B18: =SUMIF(Production_Entry!F:F,A18,Production_Entry!G:G) -> 1870 | C18: =INDEX(Pay_Item_Catalog!C:C,MATCH(A18,Pay_Item_Catalog!A:A,0)) -> FT | D18: =B18*VLOOKUP(A18,Rate_Table!B:C,2,FALSE) -> 1215.5
A19: HANDHOLE_EA | B19: =SUMIF(Production_Entry!F:F,A19,Production_Entry!G:G) -> 6 | C19: =INDEX(Pay_Item_Catalog!C:C,MATCH(A19,Pay_Item_Catalog!A:A,0)) -> EA | D19: =B19*VLOOKUP(A19,Rate_Table!B:C,2,FALSE) -> 270
A20: VAULT_EA | B20: =SUMIF(Production_Entry!F:F,A20,Production_Entry!G:G) -> 2 | C20: =INDEX(Pay_Item_Catalog!C:C,MATCH(A20,Pay_Item_Catalog!A:A,0)) -> EA | D20: =B20*VLOOKUP(A20,Rate_Table!B:C,2,FALSE) -> 170
A21: POTHOLE_EA | B21: =SUMIF(Production_Entry!F:F,A21,Production_Entry!G:G) -> 4 | C21: =INDEX(Pay_Item_Catalog!C:C,MATCH(A21,Pay_Item_Catalog!A:A,0)) -> EA | D21: =B21*VLOOKUP(A21,Rate_Table!B:C,2,FALSE) -> 140
A22: RESTORATION_SQFT | B22: =SUMIF(Production_Entry!F:F,A22,Production_Entry!G:G) -> 120 | C22: =INDEX(Pay_Item_Catalog!C:C,MATCH(A22,Pay_Item_Catalog!A:A,0)) -> SQFT | D22: =B22*VLOOKUP(A22,Rate_Table!B:C,2,FALSE) -> 300
A23: BORE_FT | B23: =SUMIF(Production_Entry!F:F,A23,Production_Entry!G:G) -> 150 | C23: =INDEX(Pay_Item_Catalog!C:C,MATCH(A23,Pay_Item_Catalog!A:A,0)) -> FT | D23: =B23*VLOOKUP(A23,Rate_Table!B:C,2,FALSE) -> 135
A24: CABLE_PULL_FT | B24: =SUMIF(Production_Entry!F:F,A24,Production_Entry!G:G) -> 800 | C24: =INDEX(Pay_Item_Catalog!C:C,MATCH(A24,Pay_Item_Catalog!A:A,0)) -> FT | D24: =B24*VLOOKUP(A24,Rate_Table!B:C,2,FALSE) -> 320
A25: CONDUIT_FT | B25: =SUMIF(Production_Entry!F:F,A25,Production_Entry!G:G) -> 200 | C25: =INDEX(Pay_Item_Catalog!C:C,MATCH(A25,Pay_Item_Catalog!A:A,0)) -> FT | D25: =B25*VLOOKUP(A25,Rate_Table!B:C,2,FALSE) -> 110
A26: REWORK_FT | B26: =SUMIF(Production_Entry!F:F,A26,Production_Entry!G:G) -> 0 | C26: =INDEX(Pay_Item_Catalog!C:C,MATCH(A26,Pay_Item_Catalog!A:A,0)) -> FT | D26: =B26*VLOOKUP(A26,Rate_Table!B:C,2,FALSE) -> 0
A27: TOTAL | B27: =SUM(B17:B26) -> 8372 | D27: =SUM(D17:D26) -> 7097.5
